twisel/__init__.py
twisel/getdata.py
twisel/save.py
twisel-0.1.11.dist-info/LICENSE
twisel-0.1.11.dist-info/METADATA
twisel-0.1.11.dist-info/WHEEL
twisel-0.1.11.dist-info/top_level.txt
twisel-0.1.11.dist-info/RECORD
