Metadata-Version: 2.1
Name: twisel
Version: 0.1.11
Summary: Library for scraping twitter with selenium
Home-page: UNKNOWN
Author: rafiksept
License: MIT
Platform: UNKNOWN
Requires-Dist: pytest
Requires-Dist: selenium
Requires-Dist: pandas
